pirogue/__init__.py
pirogue/cli.py
pirogue/exceptions.py
pirogue/information_schema.py
pirogue/multiple_inheritance.py
pirogue/simple_joins.py
pirogue/single_inheritance.py
pirogue/utils.py
pirogue-3.0.1.dist-info/licenses/LICENSE
pirogue-3.0.1.dist-info/METADATA
pirogue-3.0.1.dist-info/WHEEL
pirogue-3.0.1.dist-info/entry_points.txt
pirogue-3.0.1.dist-info/top_level.txt
pirogue-3.0.1.dist-info/RECORD
